grantt/__init__.py
grantt-0.2.0.dist-info/WHEEL
grantt-0.2.0.dist-info/entry_points.txt
grantt-0.2.0.dist-info/METADATA
grantt-0.2.0.dist-info/RECORD
