Metadata-Version: 2.3
Name: grantt
Version: 0.2.0
Summary: Making Gantt charts in matplotlib
Author: Maximilian Ramgraber, Daniel Sharp
Author-email: Maximilian Ramgraber <m.ramgraber@tudelft.nl>, Daniel Sharp <dannys4@mit.edu>
Requires-Dist: matplotlib>=3.10.5
Requires-Python: >=3.11
Project-URL: Repository, https://github.com/dannys4/granttpy.git
